om/__init__.py
om/monitor.py
om/algorithms/__init__.py
om/algorithms/_crystallography.cpython-310-x86_64-linux-gnu.so
om/algorithms/_generic.cpython-310-x86_64-linux-gnu.so
om/algorithms/calibration.py
om/algorithms/crystallography.py
om/algorithms/generic.py
om/algorithms/xes.py
om/data_retrieval_layer/__init__.py
om/data_retrieval_layer/data_event_handlers_asapo.py
om/data_retrieval_layer/data_event_handlers_files.py
om/data_retrieval_layer/data_event_handlers_http.py
om/data_retrieval_layer/data_event_handlers_psana.py
om/data_retrieval_layer/data_event_handlers_zmq.py
om/data_retrieval_layer/data_retrieval_asapo.py
om/data_retrieval_layer/data_retrieval_files.py
om/data_retrieval_layer/data_retrieval_http.py
om/data_retrieval_layer/data_retrieval_psana.py
om/data_retrieval_layer/data_retrieval_zmq.py
om/data_retrieval_layer/data_sources_asapo.py
om/data_retrieval_layer/data_sources_files.py
om/data_retrieval_layer/data_sources_generic.py
om/data_retrieval_layer/data_sources_http.py
om/data_retrieval_layer/data_sources_psana.py
om/data_retrieval_layer/data_sources_zmq.py
om/data_retrieval_layer/event_retrieval.py
om/graphical_interfaces/__init__.py
om/graphical_interfaces/common.py
om/graphical_interfaces/crystallography_gui.py
om/graphical_interfaces/crystallography_parameter_tweaker.py
om/graphical_interfaces/frame_viewer.py
om/graphical_interfaces/xes_gui.py
om/lib/__init__.py
om/lib/cheetah.py
om/lib/crystallography.py
om/lib/event_management.py
om/lib/exceptions.py
om/lib/geometry.py
om/lib/hdf5.py
om/lib/layer_management.py
om/lib/parameters.py
om/lib/rich_console.py
om/lib/xes.py
om/lib/zmq.py
om/lib/zmq_qt.py
om/parallelization_layer/__init__.py
om/parallelization_layer/mpi.py
om/parallelization_layer/multiprocessing.py
om/parallelization_layer/parallel_zmq.py
om/processing_layer/__init__.py
om/processing_layer/cheetah.py
om/processing_layer/cheetah_streaming.py
om/processing_layer/crystallography.py
ondamonitor-23.8.3.dist-info/LICENSE
ondamonitor-23.8.3.dist-info/METADATA
ondamonitor-23.8.3.dist-info/WHEEL
ondamonitor-23.8.3.dist-info/entry_points.txt
ondamonitor-23.8.3.dist-info/top_level.txt
ondamonitor-23.8.3.dist-info/RECORD
