Metadata-Version: 2.1
Name: ondamonitor
Version: 23.8.3
Summary: Real-time monitoring of x-ray imaging experiments
Home-page: https://www.ondamonitor.com
Author: OM Dev Team
Author-email: valmar@slac.stanford.edu
License: GNU General Public License v3.0
Platform: any
Classifier: Programming Language :: Python
Classifier: Programming Language :: Python :: 3
Classifier: Operating System :: OS Independent
Classifier: Topic :: Software Development :: Libraries :: Python Modules
Classifier: License :: OSI Approved :: GNU General Public License v3 or later (GPLv3+)
Classifier: Natural Language :: English
Classifier: Intended Audience :: Science/Research
Provides-Extra: qt
Provides-Extra: docs
License-File: LICENSE
